{"type": "Feature", "id": 12522818, "geometry": {"type": "Point", "coordinates": [-62.529999, 7.3439]}, "properties": {"woe:id": 12522818, "woe:parent_id": 395328, "woe:name": "Mata en Medio Airport", "woe:placetype": 14, "woe:placetype_name": "Airport", "woe:lang": "ENG", "iso:country": "VE", "meta:provider": ["geoplanet:7.3.1", "geoplanet:7.3.2", "geoplanet:7.4.0", "geoplanet:7.4.1", "geoplanet:7.5.1", "geoplanet:7.5.2", "geoplanet:7.6.0", "geoplanet:7.8.1", "geoplanet:7.9.0", "geoplanet:7.10.0", "geoplanet:8.0.0", "woeplanet:8.0.0"], "meta:indexed": "2020-08-20T20:27:03.136234", "meta:updated": "2020-10-14T11:29:27.944369", "woe:hierarchy": {"continent": 24865673, "country": 23424982, "town": 0, "planet": 1, "county": 26804699, "suburb": 0, "state": 2347682, "region": 0, "localadmin": 26805579}, "woe:timezone_id": 28350743, "woe:hash": "d979c0gj36jm", "woe:centroid": [-62.529999, 7.3439], "geom:latitude": 7.3439, "geom:longitude": -62.529999, "geom:hash": "d979c0gj36jm", "woe:latitude": 7.3439, "geom:centroid": [-62.529999, 7.3439], "woe:longitude": -62.529999, "woe:repo": "woeplanet-airport-ve", "geom:area": 0.0, "woe:scale": 19}}