{"type": "Feature", "id": 12522779, "geometry": {"type": "Point", "coordinates": [-72.463303, 10.2661]}, "properties": {"woe:id": 12522779, "woe:parent_id": 395521, "woe:name": "El Mango Airport", "woe:placetype": 14, "woe:placetype_name": "Airport", "woe:lang": "ENG", "iso:country": "VE", "meta:provider": ["geoplanet:7.3.1", "geoplanet:7.3.2", "geoplanet:7.4.0", "geoplanet:7.4.1", "geoplanet:7.5.1", "geoplanet:7.5.2", "geoplanet:7.6.0", "geoplanet:7.8.1", "geoplanet:7.9.0", "geoplanet:7.10.0", "geoplanet:8.0.0", "woeplanet:8.0.0"], "meta:indexed": "2020-08-20T20:27:03.103500", "meta:updated": "2020-10-14T11:29:27.932726", "woe:hierarchy": {"continent": 24865673, "country": 23424982, "town": 0, "planet": 1, "county": 26804447, "suburb": 0, "state": 2347699, "region": 0, "localadmin": 26805308}, "woe:timezone_id": 28350743, "woe:hash": "d3u6rhcu6etp", "woe:centroid": [-72.463303, 10.2661], "geom:latitude": 10.2661, "geom:longitude": -72.463303, "geom:hash": "d3u6rhcu6etp", "woe:latitude": 10.2661, "geom:centroid": [-72.463303, 10.2661], "woe:longitude": -72.463303, "woe:repo": "woeplanet-airport-ve", "geom:area": 0.0, "woe:scale": 19}}