{"type": "Feature", "id": 12522814, "geometry": {"type": "Point", "coordinates": [-70.25, 11.2667]}, "properties": {"woe:id": 12522814, "woe:parent_id": 395420, "woe:name": "Mamon Airport", "woe:placetype": 14, "woe:placetype_name": "Airport", "woe:lang": "ENG", "iso:country": "VE", "meta:provider": ["geoplanet:7.3.1", "geoplanet:7.3.2", "geoplanet:7.4.0", "geoplanet:7.4.1", "geoplanet:7.5.1", "geoplanet:7.5.2", "geoplanet:7.6.0", "geoplanet:7.8.1", "geoplanet:7.9.0", "geoplanet:7.10.0", "geoplanet:8.0.0", "woeplanet:8.0.0"], "meta:indexed": "2020-08-20T20:27:03.133019", "meta:updated": "2020-10-14T11:29:27.968555", "woe:hierarchy": {"continent": 24865673, "country": 23424982, "town": 0, "planet": 1, "county": 26804482, "suburb": 0, "state": 2347687, "region": 0, "localadmin": 26805437}, "woe:timezone_id": 28350743, "woe:hash": "d6n017j92357", "woe:centroid": [-70.25, 11.2667], "geom:latitude": 11.2667, "geom:longitude": -70.25, "geom:hash": "d6n017j92357", "woe:latitude": 11.2667, "geom:centroid": [-70.25, 11.2667], "woe:longitude": -70.25, "woe:repo": "woeplanet-airport-ve", "geom:area": 0.0, "woe:scale": 19}}