{"type": "Feature", "id": 12522842, "geometry": {"type": "Point", "coordinates": [-67.440598, 7.8856]}, "properties": {"woe:id": 12522842, "woe:parent_id": 393489, "woe:name": "San Fernando de Apure Airport", "woe:placetype": 14, "woe:placetype_name": "Airport", "woe:lang": "ENG", "iso:country": "VE", "meta:provider": ["geoplanet:7.3.1", "geoplanet:7.3.2", "geoplanet:7.4.0", "geoplanet:7.4.1", "geoplanet:7.5.1", "geoplanet:7.5.2", "geoplanet:7.6.0", "geoplanet:7.8.1", "geoplanet:7.9.0", "geoplanet:7.10.0", "geoplanet:8.0.0", "woeplanet:8.0.0"], "meta:indexed": "2020-08-20T20:27:03.156429", "woe:alias_ENG_V": ["SFD Airport", "SFD", "San Fernando Apure", "San Fernando Apure Airport"], "meta:updated": "2020-10-14T11:29:27.945924", "woe:hierarchy": {"continent": 24865673, "country": 23424982, "town": 0, "planet": 1, "county": 26804553, "suburb": 0, "state": 2347679, "region": 0, "localadmin": 26805705}, "woe:timezone_id": 28350743, "woe:hash": "d92hc7e2bnmk", "woe:centroid": [-67.440598, 7.8856], "geom:latitude": 7.8856, "geom:longitude": -67.440598, "geom:hash": "d92hc7e2bnmk", "woe:latitude": 7.8856, "geom:centroid": [-67.440598, 7.8856], "woe:longitude": -67.440598, "woe:repo": "woeplanet-airport-ve", "geom:area": 0.0, "woe:scale": 19}}