{"type": "Feature", "id": 12522766, "properties": {"woe:id": 12522766, "woe:parent_id": 468392, "woe:name": "Carora Airport", "woe:placetype": 14, "woe:placetype_name": "Airport", "woe:lang": "ENG", "iso:country": "VE", "meta:provider": ["geoplanet:7.3.1", "geoplanet:7.3.2", "geoplanet:7.4.0", "geoplanet:7.4.1", "geoplanet:7.5.1", "geoplanet:7.5.2", "geoplanet:7.6.0", "geoplanet:7.8.1", "geoplanet:7.9.0", "geoplanet:7.10.0", "geoplanet:8.0.0", "woeplanet:8.0.0"], "meta:indexed": "2020-08-20T20:27:03.094935", "woe:alias_ENG_V": ["VCR Airport", "VCR"], "meta:updated": "2020-08-22T02:46:39.325230", "woe:hierarchy": {"continent": 24865673, "country": 23424982, "town": 0, "planet": 1, "county": 26804465, "suburb": 0, "state": 2347689, "region": 0, "localadmin": 26805341}, "woe:timezone_id": 28350743, "woe:hash": "d3y1vth4ph7v", "woe:centroid": [-70.065002, 10.1792], "geom:latitude": 10.1792, "geom:longitude": -70.065002, "geom:hash": "d3y1vth4ph7v", "woe:latitude": 10.1792, "geom:centroid": [-70.065002, 10.1792], "woe:longitude": -70.065002, "woe:repo": "woeplanet-airport-ve"}, "geometry": {"coordinates": [-70.065002, 10.1792], "type": "Point"}}