{"type": "Feature", "id": 12522813, "properties": {"woe:id": 12522813, "woe:parent_id": 395351, "woe:name": "Luepa Airport", "woe:placetype": 14, "woe:placetype_name": "Airport", "woe:lang": "ENG", "iso:country": "VE", "meta:provider": ["geoplanet:7.3.1", "geoplanet:7.3.2", "geoplanet:7.4.0", "geoplanet:7.4.1", "geoplanet:7.5.1", "geoplanet:7.5.2", "geoplanet:7.6.0", "geoplanet:7.8.1", "geoplanet:7.9.0", "geoplanet:7.10.0", "geoplanet:8.0.0", "woeplanet:8.0.0"], "meta:indexed": "2020-08-20T20:27:03.132208", "meta:updated": "2020-08-22T02:46:39.345401", "woe:hierarchy": {"continent": 24865673, "country": 23424982, "town": 0, "planet": 1, "county": 26804568, "suburb": 0, "state": 2347682, "region": 0, "localadmin": 26805588}, "woe:timezone_id": 28350743, "woe:hash": "d9h2cy5vye6e", "woe:centroid": [-61.441101, 5.7908], "geom:latitude": 5.7908, "geom:longitude": -61.441101, "geom:hash": "d9h2cy5vye6e", "woe:latitude": 5.7908, "geom:centroid": [-61.441101, 5.7908], "woe:longitude": -61.441101, "woe:repo": "woeplanet-airport-ve"}, "geometry": {"coordinates": [-61.441101, 5.7908], "type": "Point"}}